harlequin_databend/__init__.py
harlequin_databend/adapter.py
harlequin_databend/cli_options.py
harlequin_databend/completions.py
harlequin_databend/py.typed
harlequin_databend-0.1.22.dist-info/METADATA
harlequin_databend-0.1.22.dist-info/WHEEL
harlequin_databend-0.1.22.dist-info/entry_points.txt
harlequin_databend-0.1.22.dist-info/RECORD
