Metadata-Version: 2.1
Name: harlequin-databend
Version: 0.1.22
Summary: A Harlequin adapter for Databend.
Home-page: https://github.com/datafuselabs/databend
License: MIT
Keywords: databend,harlequin
Author: hanxuanliang
Author-email: hxuanliang@163.com
Requires-Python: >=3.10,<4.0
Classifier: License :: OSI Approved :: MIT License
Classifier: Programming Language :: Python :: 3
Classifier: Programming Language :: Python :: 3.10
Classifier: Programming Language :: Python :: 3.11
Classifier: Programming Language :: Python :: 3.12
Requires-Dist: databend-py (>=0.6.0,<0.7.0)
Requires-Dist: harlequin (>=1.20.0,<2.0.0)
Requires-Dist: pandas (>=2.2.2,<3.0.0)
Requires-Dist: pyarrow (>=16.1.0,<17.0.0)
